{"title":"Body","body":{"content":{"application/json":{"schema":{"type":"object","default":null,"description":"Create a per-book risk limit","properties":{"bookId":{"type":"string","format":"uuid","default":"","description":"Governed book UUID"},"metric":{"type":"string","default":"","description":"Governed metric: dv01, duration, vega, notional, market_value","minLength":1},"limitAmount":{"type":"number","default":"","description":"Cap amount (positive)"},"currency":{"type":"string","default":"","description":"ISO 4217 currency","maxLength":3,"minLength":3},"effectiveDate":{"type":"string","format":"date","default":"","description":"Effective date"},"expiryDate":{"type":"string","format":"date","default":"","description":"Expiry date; omit for open-ended"}},"required":["bookId","currency","effectiveDate","limitAmount","metric"],"title":"CreateRiskLimitRequestDto"}}},"required":true}}