{"responses":{"200":{"description":"Comparable peer-set returned","content":{"*/*":{"schema":{"type":"object","default":null,"description":"Comparable bond peer-set for relative-value analysis","properties":{"reference":{"type":"object","properties":{"id":{"type":"string","format":"uuid"},"issuer":{"type":"string"},"sector":{"type":"string"},"rating":{"type":"string"},"tenorYears":{"type":"number"}},"title":"ReferenceDto"},"peers":{"type":"array","items":{"type":"object","properties":{"id":{"type":"string","format":"uuid"},"isin":{"type":"string"},"issuer":{"type":"string"},"sector":{"type":"string"},"rating":{"type":"string"},"tenorYears":{"type":"number"},"zSpreadBps":{"type":"number"},"gSpreadBps":{"type":"number"},"yield":{"type":"number"},"liquidityScore":{"type":"number"},"proxy":{"type":"boolean"},"matchBasis":{"type":"array","items":{"type":"string"}}},"title":"PeerDto"}}},"title":"InstrumentComparablesResponseDto"}}}},"400":{"description":"Invalid limit or unsupported instrument type","content":{"*/*":{"schema":{"type":"object","default":null,"description":"Comparable bond peer-set for relative-value analysis","properties":{"reference":{"type":"object","properties":{"id":{"type":"string","format":"uuid"},"issuer":{"type":"string"},"sector":{"type":"string"},"rating":{"type":"string"},"tenorYears":{"type":"number"}},"title":"ReferenceDto"},"peers":{"type":"array","items":{"type":"object","properties":{"id":{"type":"string","format":"uuid"},"isin":{"type":"string"},"issuer":{"type":"string"},"sector":{"type":"string"},"rating":{"type":"string"},"tenorYears":{"type":"number"},"zSpreadBps":{"type":"number"},"gSpreadBps":{"type":"number"},"yield":{"type":"number"},"liquidityScore":{"type":"number"},"proxy":{"type":"boolean"},"matchBasis":{"type":"array","items":{"type":"string"}}},"title":"PeerDto"}}},"title":"InstrumentComparablesResponseDto"}}}},"403":{"description":"Insufficient scope — requires pretrade:read","content":{"*/*":{"schema":{"type":"object","default":null,"description":"Comparable bond peer-set for relative-value analysis","properties":{"reference":{"type":"object","properties":{"id":{"type":"string","format":"uuid"},"issuer":{"type":"string"},"sector":{"type":"string"},"rating":{"type":"string"},"tenorYears":{"type":"number"}},"title":"ReferenceDto"},"peers":{"type":"array","items":{"type":"object","properties":{"id":{"type":"string","format":"uuid"},"isin":{"type":"string"},"issuer":{"type":"string"},"sector":{"type":"string"},"rating":{"type":"string"},"tenorYears":{"type":"number"},"zSpreadBps":{"type":"number"},"gSpreadBps":{"type":"number"},"yield":{"type":"number"},"liquidityScore":{"type":"number"},"proxy":{"type":"boolean"},"matchBasis":{"type":"array","items":{"type":"string"}}},"title":"PeerDto"}}},"title":"InstrumentComparablesResponseDto"}}}},"404":{"description":"Instrument not found","content":{"*/*":{"schema":{"type":"object","default":null,"description":"Comparable bond peer-set for relative-value analysis","properties":{"reference":{"type":"object","properties":{"id":{"type":"string","format":"uuid"},"issuer":{"type":"string"},"sector":{"type":"string"},"rating":{"type":"string"},"tenorYears":{"type":"number"}},"title":"ReferenceDto"},"peers":{"type":"array","items":{"type":"object","properties":{"id":{"type":"string","format":"uuid"},"isin":{"type":"string"},"issuer":{"type":"string"},"sector":{"type":"string"},"rating":{"type":"string"},"tenorYears":{"type":"number"},"zSpreadBps":{"type":"number"},"gSpreadBps":{"type":"number"},"yield":{"type":"number"},"liquidityScore":{"type":"number"},"proxy":{"type":"boolean"},"matchBasis":{"type":"array","items":{"type":"string"}}},"title":"PeerDto"}}},"title":"InstrumentComparablesResponseDto"}}}}}}