{"responses":{"200":{"description":"All pre-trade checks passed","content":{"*/*":{"schema":{"type":"object","properties":{"passed":{"type":"boolean"},"checks":{"type":"array","items":{"type":"object","properties":{"checkName":{"type":"string"},"passed":{"type":"boolean"},"detail":{"type":"string"}},"title":"CheckResultDto"}},"summary":{"type":"string"}},"title":"PreTradeCheckResponseDto"}}}},"422":{"description":"One or more pre-trade checks failed","content":{"*/*":{"schema":{"type":"object","properties":{"passed":{"type":"boolean"},"checks":{"type":"array","items":{"type":"object","properties":{"checkName":{"type":"string"},"passed":{"type":"boolean"},"detail":{"type":"string"}},"title":"CheckResultDto"}},"summary":{"type":"string"}},"title":"PreTradeCheckResponseDto"}}}},"503":{"description":"Pre-trade check engine not available","content":{"*/*":{"schema":{"type":"object","properties":{"passed":{"type":"boolean"},"checks":{"type":"array","items":{"type":"object","properties":{"checkName":{"type":"string"},"passed":{"type":"boolean"},"detail":{"type":"string"}},"title":"CheckResultDto"}},"summary":{"type":"string"}},"title":"PreTradeCheckResponseDto"}}}}}}